framalytics/FRAM_Visualizer.py
framalytics/__init__.py
framalytics/fram.py
framalytics/xfmv_parser.py
framalytics/tests/__init__.py
framalytics/tests/test_fram.py
framalytics/tests/test_xfmv_parser.py
ra_framalytics-1.1.0.dist-info/LICENSE
ra_framalytics-1.1.0.dist-info/METADATA
ra_framalytics-1.1.0.dist-info/WHEEL
ra_framalytics-1.1.0.dist-info/top_level.txt
ra_framalytics-1.1.0.dist-info/RECORD
