Metadata-Version: 2.1
Name: ra-framalytics
Version: 1.1.0
Summary: Python tools for the Functional Resonance Analysis Method (FRAM) - Fork for RA-FRAM
Author-email: "Terrence S. Tricco" <tstricco@mun.ca>, Gabrio Mauri <gabrio.mauri@gmail.com>
Project-URL: Homepage, https://github.com/sgabb/framalytics
Project-URL: Documentation, https://framalytics.readthedocs.io
Project-URL: Repository, https://github.com/sgabb/framalytics
Project-URL: Issues, https://github.com/sgabb/framalytics/issues
Project-URL: Original, https://github.com/ttricco/framalytics
Keywords: FRAM,risk-assessment,systems-analysis,functional-resonance,safety-analysis
Classifier: License :: OSI Approved :: GNU General Public License v3 or later (GPLv3+)
Classifier: Intended Audience :: Science/Research
Classifier: Programming Language :: Python :: 3
Classifier: Programming Language :: Python :: 3.10
Classifier: Programming Language :: Python :: 3.11
Classifier: Programming Language :: Python :: 3.12
Classifier: Topic :: Scientific/Engineering
Classifier: Topic :: Scientific/Engineering :: Information Analysis
Classifier: Development Status :: 4 - Beta
Classifier: Operating System :: OS Independent
Requires-Python: >=3.10
License-File: LICENSE
Requires-Dist: pandas>=2.2.2
Requires-Dist: matplotlib>=3.8.4
Requires-Dist: numpy>=2.0.0
Provides-Extra: dev
Requires-Dist: pytest>=7.0; extra == "dev"
Requires-Dist: sphinx>=5.0; extra == "dev"
Requires-Dist: black>=22.0; extra == "dev"
Requires-Dist: mypy>=0.990; extra == "dev"
